{
  "annualized_apy": 5.42542731173892,
  "baseline_sol": 25.0,
  "days_elapsed": 28.824826388888887,
  "deployed_at": "2026-05-03T18:05:00Z",
  "legs": {
    "inf": {
      "amount_token": 3.518819517,
      "baseline_price_sol_per_token": 1.421,
      "current_price_sol_per_token": 1.4323325083540424,
      "label": "INF",
      "mint": "5oVNBeEEQvYi1cX3ir8Dx5n1P7pdxydbGF2X4TxVusJm",
      "yield_sol": 0.03987705157276964
    },
    "jitosol": {
      "amount_token": 15.661410365,
      "baseline_price_sol_per_token": 1.277,
      "current_price_sol_per_token": 1.2812931850107447,
      "label": "JitoSOL",
      "mint": "J1toso1uCk3RLmjorhTtrVwY9HJ7X8V9yYac6Y7kGCPn",
      "yield_sol": 0.06723733222614166
    }
  },
  "snapshot_at": "2026-06-01T13:52:45Z",
  "sources": {
    "inf": {
      "provider": "jupiter-price-v3",
      "sol_usd": 79.71154010544866,
      "token_usd": 114.17343018400112,
      "url": "https://lite-api.jup.ag/price/v3?ids=5oVNBeEEQvYi1cX3ir8Dx5n1P7pdxydbGF2X4TxVusJm,So11111111111111111111111111111111111111112"
    },
    "jitosol": {
      "provider": "jupiter-price-v3",
      "sol_usd": 79.71154010544866,
      "token_usd": 102.13385310382203,
      "url": "https://lite-api.jup.ag/price/v3?ids=J1toso1uCk3RLmjorhTtrVwY9HJ7X8V9yYac6Y7kGCPn,So11111111111111111111111111111111111111112"
    }
  },
  "yield_pct_total": 0.4284575351956452,
  "yield_sol_inf": 0.03987705157276964,
  "yield_sol_jitosol": 0.06723733222614166,
  "yield_sol_total": 0.1071143837989113
}
