{
  "annualized_apy": 5.218986799184189,
  "baseline_sol": 25.0,
  "days_elapsed": 58.94675925925926,
  "deployed_at": "2026-05-03T18:05:00Z",
  "legs": {
    "inf": {
      "amount_token": 3.518819517,
      "baseline_price_sol_per_token": 1.421,
      "current_price_sol_per_token": 1.4339782087427062,
      "label": "INF",
      "mint": "5oVNBeEEQvYi1cX3ir8Dx5n1P7pdxydbGF2X4TxVusJm",
      "yield_sol": 0.04566797421953448
    },
    "jitosol": {
      "amount_token": 15.661410365,
      "baseline_price_sol_per_token": 1.277,
      "current_price_sol_per_token": 1.2875383848621065,
      "label": "JitoSOL",
      "mint": "J1toso1uCk3RLmjorhTtrVwY9HJ7X8V9yYac6Y7kGCPn",
      "yield_sol": 0.16504596990975484
    }
  },
  "snapshot_at": "2026-07-01T16:48:20Z",
  "sources": {
    "inf": {
      "provider": "jupiter-price-v3",
      "sol_usd": 77.41807428869451,
      "token_usd": 111.01583149281191,
      "url": "https://lite-api.jup.ag/price/v3?ids=5oVNBeEEQvYi1cX3ir8Dx5n1P7pdxydbGF2X4TxVusJm,So11111111111111111111111111111111111111112"
    },
    "jitosol": {
      "provider": "jupiter-price-v3",
      "sol_usd": 77.41807428869451,
      "token_usd": 99.6787423288003,
      "url": "https://lite-api.jup.ag/price/v3?ids=J1toso1uCk3RLmjorhTtrVwY9HJ7X8V9yYac6Y7kGCPn,So11111111111111111111111111111111111111112"
    }
  },
  "yield_pct_total": 0.8428557765171574,
  "yield_sol_inf": 0.04566797421953448,
  "yield_sol_jitosol": 0.16504596990975484,
  "yield_sol_total": 0.21071394412928932
}
