{
  "annualized_apy": 0.831197728035529,
  "baseline_sol": 25.0,
  "days_elapsed": 31.191898148148148,
  "deployed_at": "2026-05-03T18:05:00Z",
  "legs": {
    "inf": {
      "amount_token": 3.518819517,
      "baseline_price_sol_per_token": 1.421,
      "current_price_sol_per_token": 1.4234125406389442,
      "label": "INF",
      "mint": "5oVNBeEEQvYi1cX3ir8Dx5n1P7pdxydbGF2X4TxVusJm",
      "yield_sol": 0.008489295085872284
    },
    "jitosol": {
      "amount_token": 15.661410365,
      "baseline_price_sol_per_token": 1.277,
      "current_price_sol_per_token": 1.2775918160491166,
      "label": "JitoSOL",
      "mint": "J1toso1uCk3RLmjorhTtrVwY9HJ7X8V9yYac6Y7kGCPn",
      "yield_sol": 0.009268674005810159
    }
  },
  "snapshot_at": "2026-06-03T22:41:20Z",
  "sources": {
    "inf": {
      "provider": "jupiter-price-v3",
      "sol_usd": 72.27864450618063,
      "token_usd": 102.88232901048163,
      "url": "https://lite-api.jup.ag/price/v3?ids=5oVNBeEEQvYi1cX3ir8Dx5n1P7pdxydbGF2X4TxVusJm,So11111111111111111111111111111111111111112"
    },
    "jitosol": {
      "provider": "jupiter-price-v3",
      "sol_usd": 72.27864450618063,
      "token_usd": 92.34260469621981,
      "url": "https://lite-api.jup.ag/price/v3?ids=J1toso1uCk3RLmjorhTtrVwY9HJ7X8V9yYac6Y7kGCPn,So11111111111111111111111111111111111111112"
    }
  },
  "yield_pct_total": 0.07103187636672978,
  "yield_sol_inf": 0.008489295085872284,
  "yield_sol_jitosol": 0.009268674005810159,
  "yield_sol_total": 0.017757969091682445
}
