{
  "annualized_apy": 5.405478864615197,
  "baseline_sol": 25.0,
  "days_elapsed": 55.42144675925926,
  "deployed_at": "2026-05-03T18:05:00Z",
  "legs": {
    "inf": {
      "amount_token": 3.518819517,
      "baseline_price_sol_per_token": 1.421,
      "current_price_sol_per_token": 1.4342054092943286,
      "label": "INF",
      "mint": "5oVNBeEEQvYi1cX3ir8Dx5n1P7pdxydbGF2X4TxVusJm",
      "yield_sol": 0.04646745195485654
    },
    "jitosol": {
      "amount_token": 15.661410365,
      "baseline_price_sol_per_token": 1.277,
      "current_price_sol_per_token": 1.2871347167777922,
      "label": "JitoSOL",
      "mint": "J1toso1uCk3RLmjorhTtrVwY9HJ7X8V9yYac6Y7kGCPn",
      "yield_sol": 0.158723958390056
    }
  },
  "snapshot_at": "2026-06-28T04:11:53Z",
  "sources": {
    "inf": {
      "provider": "jupiter-price-v3",
      "sol_usd": 70.68603386006221,
      "token_usd": 101.3782921236633,
      "url": "https://lite-api.jup.ag/price/v3?ids=5oVNBeEEQvYi1cX3ir8Dx5n1P7pdxydbGF2X4TxVusJm,So11111111111111111111111111111111111111112"
    },
    "jitosol": {
      "provider": "jupiter-price-v3",
      "sol_usd": 70.68603386006221,
      "token_usd": 90.9824481726166,
      "url": "https://lite-api.jup.ag/price/v3?ids=J1toso1uCk3RLmjorhTtrVwY9HJ7X8V9yYac6Y7kGCPn,So11111111111111111111111111111111111111112"
    }
  },
  "yield_pct_total": 0.8207656413796502,
  "yield_sol_inf": 0.04646745195485654,
  "yield_sol_jitosol": 0.158723958390056,
  "yield_sol_total": 0.20519141034491256
}
