{
  "annualized_apy": 4.778925839987387,
  "baseline_sol": 25.0,
  "days_elapsed": 67.1478125,
  "deployed_at": "2026-05-03T18:05:00Z",
  "legs": {
    "inf": {
      "amount_token": 3.518819517,
      "baseline_price_sol_per_token": 1.421,
      "current_price_sol_per_token": 1.4337804081245942,
      "label": "INF",
      "mint": "5oVNBeEEQvYi1cX3ir8Dx5n1P7pdxydbGF2X4TxVusJm",
      "yield_sol": 0.0449719495440472
    },
    "jitosol": {
      "amount_token": 15.661410365,
      "baseline_price_sol_per_token": 1.277,
      "current_price_sol_per_token": 1.2881623884724724,
      "label": "JitoSOL",
      "mint": "J1toso1uCk3RLmjorhTtrVwY9HJ7X8V9yYac6Y7kGCPn",
      "yield_sol": 0.1748187465209378
    }
  },
  "snapshot_at": "2026-07-09T21:37:51Z",
  "sources": {
    "inf": {
      "provider": "jupiter-price-v3",
      "sol_usd": 77.99254214235472,
      "token_usd": 111.82417890353996,
      "url": "https://lite-api.jup.ag/price/v3?ids=5oVNBeEEQvYi1cX3ir8Dx5n1P7pdxydbGF2X4TxVusJm,So11111111111111111111111111111111111111112"
    },
    "jitosol": {
      "provider": "jupiter-price-v3",
      "sol_usd": 77.99459349269729,
      "token_usd": 100.4697018414925,
      "url": "https://lite-api.jup.ag/price/v3?ids=J1toso1uCk3RLmjorhTtrVwY9HJ7X8V9yYac6Y7kGCPn,So11111111111111111111111111111111111111112"
    }
  },
  "yield_pct_total": 0.87916278425994,
  "yield_sol_inf": 0.0449719495440472,
  "yield_sol_jitosol": 0.1748187465209378,
  "yield_sol_total": 0.219790696064985
}
