{
  "annualized_apy": 4.909201088718177,
  "baseline_sol": 25.0,
  "days_elapsed": 48.894375,
  "deployed_at": "2026-05-03T18:05:00Z",
  "legs": {
    "inf": {
      "amount_token": 3.518819517,
      "baseline_price_sol_per_token": 1.421,
      "current_price_sol_per_token": 1.4281421752150405,
      "label": "INF",
      "mint": "5oVNBeEEQvYi1cX3ir8Dx5n1P7pdxydbGF2X4TxVusJm",
      "yield_sol": 0.025132025540518035
    },
    "jitosol": {
      "amount_token": 15.661410365,
      "baseline_price_sol_per_token": 1.277,
      "current_price_sol_per_token": 1.2858927924846244,
      "label": "JitoSOL",
      "mint": "J1toso1uCk3RLmjorhTtrVwY9HJ7X8V9yYac6Y7kGCPn",
      "yield_sol": 0.13927367239249208
    }
  },
  "snapshot_at": "2026-06-21T15:32:54Z",
  "sources": {
    "inf": {
      "provider": "jupiter-price-v3",
      "sol_usd": 74.01940783716094,
      "token_usd": 105.71023811669224,
      "url": "https://lite-api.jup.ag/price/v3?ids=5oVNBeEEQvYi1cX3ir8Dx5n1P7pdxydbGF2X4TxVusJm,So11111111111111111111111111111111111111112"
    },
    "jitosol": {
      "provider": "jupiter-price-v3",
      "sol_usd": 74.01458582925164,
      "token_usd": 95.1748224565693,
      "url": "https://lite-api.jup.ag/price/v3?ids=J1toso1uCk3RLmjorhTtrVwY9HJ7X8V9yYac6Y7kGCPn,So11111111111111111111111111111111111111112"
    }
  },
  "yield_pct_total": 0.6576227917320405,
  "yield_sol_inf": 0.025132025540518035,
  "yield_sol_jitosol": 0.13927367239249208,
  "yield_sol_total": 0.16440569793301013
}
