{
  "annualized_apy": 5.368854162489653,
  "baseline_sol": 25.0,
  "days_elapsed": 43.64825231481481,
  "deployed_at": "2026-05-03T18:05:00Z",
  "legs": {
    "inf": {
      "amount_token": 3.518819517,
      "baseline_price_sol_per_token": 1.421,
      "current_price_sol_per_token": 1.4308751257350072,
      "label": "INF",
      "mint": "5oVNBeEEQvYi1cX3ir8Dx5n1P7pdxydbGF2X4TxVusJm",
      "yield_sol": 0.03474878516917213
    },
    "jitosol": {
      "amount_token": 15.661410365,
      "baseline_price_sol_per_token": 1.277,
      "current_price_sol_per_token": 1.2850298527023267,
      "label": "JitoSOL",
      "mint": "J1toso1uCk3RLmjorhTtrVwY9HJ7X8V9yYac6Y7kGCPn",
      "yield_sol": 0.1257588183416444
    }
  },
  "snapshot_at": "2026-06-16T09:38:29Z",
  "sources": {
    "inf": {
      "provider": "jupiter-price-v3",
      "sol_usd": 74.87300109259473,
      "token_usd": 107.13391485252382,
      "url": "https://lite-api.jup.ag/price/v3?ids=5oVNBeEEQvYi1cX3ir8Dx5n1P7pdxydbGF2X4TxVusJm,So11111111111111111111111111111111111111112"
    },
    "jitosol": {
      "provider": "jupiter-price-v3",
      "sol_usd": 74.87300109259473,
      "token_usd": 96.21404156539816,
      "url": "https://lite-api.jup.ag/price/v3?ids=J1toso1uCk3RLmjorhTtrVwY9HJ7X8V9yYac6Y7kGCPn,So11111111111111111111111111111111111111112"
    }
  },
  "yield_pct_total": 0.6420304140432661,
  "yield_sol_inf": 0.03474878516917213,
  "yield_sol_jitosol": 0.1257588183416444,
  "yield_sol_total": 0.16050760351081653
}
